simple_image_compressor/__init__.py
simple_image_compressor/__main__.py
simple_image_compressor/res/settings.json
simple_image_compressor/src/__init__.py
simple_image_compressor/src/compressor.py
simple_image_compressor/src/job.py
simple_image_compressor/src/main.py
simple_image_compressor/src/settings.py
simple_image_compressor-0.1.2.dist-info/LICENSE
simple_image_compressor-0.1.2.dist-info/METADATA
simple_image_compressor-0.1.2.dist-info/WHEEL
simple_image_compressor-0.1.2.dist-info/entry_points.txt
simple_image_compressor-0.1.2.dist-info/top_level.txt
simple_image_compressor-0.1.2.dist-info/RECORD
