Metadata-Version: 2.1
Name: simple-image-compressor
Version: 0.1.2
Summary: Simple utility to compress images on a given path
Home-page: https://github.com/sebastianserrani/simple_image_compressor/
Author: Sebastian Serrani
License: MIT
Keywords: image,compression,recursion,process,multiprocess,queue
Platform: UNKNOWN
Classifier: Development Status :: 4 - Beta
Classifier: Environment :: Console
Classifier: Intended Audience :: Developers
Classifier: Intended Audience :: System Administrators
Classifier: License :: OSI Approved :: MIT License
Classifier: Operating System :: OS Independent
Classifier: Programming Language :: Python :: 3
Classifier: Topic :: Multimedia :: Graphics
Classifier: Topic :: System :: Archiving :: Compression
Classifier: Topic :: System :: Systems Administration
Requires-Python: >=3.8
Requires-Dist: Pillow (>=8.3.0)
